{
  "title": "S3MultipartHandler",
  "lang": "it",
  "document": {
    "type": "document",
    "title": "S3MultipartHandler",
    "sections": [
      {
        "type": "section",
        "id": "_s3multiparthandler",
        "title": "S3MultipartHandler",
        "level": 1,
        "blocks": [
          {
            "type": "table",
            "headers": [
              {
                "text": "Element",
                "colspan": 1,
                "rowspan": 1
              },
              {
                "text": "Missed Instructions",
                "colspan": 1,
                "rowspan": 1
              },
              {
                "text": "Cov.",
                "colspan": 1,
                "rowspan": 1
              },
              {
                "text": "Missed Branches",
                "colspan": 1,
                "rowspan": 1
              },
              {
                "text": "Cov.",
                "colspan": 1,
                "rowspan": 1
              },
              {
                "text": "Missed",
                "colspan": 1,
                "rowspan": 1
              },
              {
                "text": "Cxty",
                "colspan": 1,
                "rowspan": 1
              },
              {
                "text": "Missed",
                "colspan": 1,
                "rowspan": 1
              },
              {
                "text": "Lines",
                "colspan": 1,
                "rowspan": 1
              },
              {
                "text": "Missed",
                "colspan": 1,
                "rowspan": 1
              },
              {
                "text": "Methods",
                "colspan": 1,
                "rowspan": 1
              }
            ],
            "rows": [
              [
                {
                  "text": "Element",
                  "colspan": 1,
                  "rowspan": 1
                },
                {
                  "text": "Missed Instructions",
                  "colspan": 1,
                  "rowspan": 1
                },
                {
                  "text": "Cov.",
                  "colspan": 1,
                  "rowspan": 1
                },
                {
                  "text": "Missed Branches",
                  "colspan": 1,
                  "rowspan": 1
                },
                {
                  "text": "Cov.",
                  "colspan": 1,
                  "rowspan": 1
                },
                {
                  "text": "Missed",
                  "colspan": 1,
                  "rowspan": 1
                },
                {
                  "text": "Cxty",
                  "colspan": 1,
                  "rowspan": 1
                },
                {
                  "text": "Missed",
                  "colspan": 1,
                  "rowspan": 1
                },
                {
                  "text": "Lines",
                  "colspan": 1,
                  "rowspan": 1
                },
                {
                  "text": "Missed",
                  "colspan": 1,
                  "rowspan": 1
                },
                {
                  "text": "Methods",
                  "colspan": 1,
                  "rowspan": 1
                }
              ],
              [
                {
                  "text": "Total",
                  "colspan": 1,
                  "rowspan": 1
                },
                {
                  "text": "78 of 388",
                  "colspan": 1,
                  "rowspan": 1
                },
                {
                  "text": "79%",
                  "colspan": 1,
                  "rowspan": 1
                },
                {
                  "text": "2 of 2",
                  "colspan": 1,
                  "rowspan": 1
                },
                {
                  "text": "0%",
                  "colspan": 1,
                  "rowspan": 1
                },
                {
                  "text": "3",
                  "colspan": 1,
                  "rowspan": 1
                },
                {
                  "text": "19",
                  "colspan": 1,
                  "rowspan": 1
                },
                {
                  "text": "22",
                  "colspan": 1,
                  "rowspan": 1
                },
                {
                  "text": "104",
                  "colspan": 1,
                  "rowspan": 1
                },
                {
                  "text": "2",
                  "colspan": 1,
                  "rowspan": 1
                },
                {
                  "text": "18",
                  "colspan": 1,
                  "rowspan": 1
                }
              ],
              [
                {
                  "text": "<a href=\"S3MultipartHandler.java.json#L60\" class=\"el_method\">uploadPartCopy(ServerRequest)</a>",
                  "colspan": 1,
                  "rowspan": 1
                },
                {
                  "text": "<img src=\"/docs/jacoco-resources/redbar.gif\" width=\"120\" height=\"10\" title=\"54\" alt=\"54\">",
                  "colspan": 1,
                  "rowspan": 1
                },
                {
                  "text": "0%",
                  "colspan": 1,
                  "rowspan": 1
                },
                {
                  "text": "<img src=\"/docs/jacoco-resources/redbar.gif\" width=\"120\" height=\"10\" title=\"2\" alt=\"2\">",
                  "colspan": 1,
                  "rowspan": 1
                },
                {
                  "text": "0%",
                  "colspan": 1,
                  "rowspan": 1
                },
                {
                  "text": "2",
                  "colspan": 1,
                  "rowspan": 1
                },
                {
                  "text": "2",
                  "colspan": 1,
                  "rowspan": 1
                },
                {
                  "text": "14",
                  "colspan": 1,
                  "rowspan": 1
                },
                {
                  "text": "14",
                  "colspan": 1,
                  "rowspan": 1
                },
                {
                  "text": "1",
                  "colspan": 1,
                  "rowspan": 1
                },
                {
                  "text": "1",
                  "colspan": 1,
                  "rowspan": 1
                }
              ],
              [
                {
                  "text": "<a href=\"S3MultipartHandler.java.json#L73\" class=\"el_method\">lambda$uploadPartCopy$0(int, MultipartUpload)</a>",
                  "colspan": 1,
                  "rowspan": 1
                },
                {
                  "text": "<img src=\"/docs/jacoco-resources/redbar.gif\" width=\"53\" height=\"10\" title=\"24\" alt=\"24\">",
                  "colspan": 1,
                  "rowspan": 1
                },
                {
                  "text": "0%",
                  "colspan": 1,
                  "rowspan": 1
                },
                {
                  "text": "",
                  "colspan": 1,
                  "rowspan": 1
                },
                {
                  "text": "n/a",
                  "colspan": 1,
                  "rowspan": 1
                },
                {
                  "text": "1",
                  "colspan": 1,
                  "rowspan": 1
                },
                {
                  "text": "1",
                  "colspan": 1,
                  "rowspan": 1
                },
                {
                  "text": "8",
                  "colspan": 1,
                  "rowspan": 1
                },
                {
                  "text": "8",
                  "colspan": 1,
                  "rowspan": 1
                },
                {
                  "text": "1",
                  "colspan": 1,
                  "rowspan": 1
                },
                {
                  "text": "1",
                  "colspan": 1,
                  "rowspan": 1
                }
              ],
              [
                {
                  "text": "<a href=\"S3MultipartHandler.java.json#L90\" class=\"el_method\">uploadPart(ServerRequest)</a>",
                  "colspan": 1,
                  "rowspan": 1
                },
                {
                  "text": "<img src=\"/docs/jacoco-resources/greenbar.gif\" width=\"100\" height=\"10\" title=\"45\" alt=\"45\">",
                  "colspan": 1,
                  "rowspan": 1
                },
                {
                  "text": "100%",
                  "colspan": 1,
                  "rowspan": 1
                },
                {
                  "text": "",
                  "colspan": 1,
                  "rowspan": 1
                },
                {
                  "text": "n/a",
                  "colspan": 1,
                  "rowspan": 1
                },
                {
                  "text": "0",
                  "colspan": 1,
                  "rowspan": 1
                },
                {
                  "text": "1",
                  "colspan": 1,
                  "rowspan": 1
                },
                {
                  "text": "0",
                  "colspan": 1,
                  "rowspan": 1
                },
                {
                  "text": "10",
                  "colspan": 1,
                  "rowspan": 1
                },
                {
                  "text": "0",
                  "colspan": 1,
                  "rowspan": 1
                },
                {
                  "text": "1",
                  "colspan": 1,
                  "rowspan": 1
                }
              ],
              [
                {
                  "text": "<a href=\"S3MultipartHandler.java.json#L116\" class=\"el_method\">completeMultipartUpload(ServerRequest)</a>",
                  "colspan": 1,
                  "rowspan": 1
                },
                {
                  "text": "<img src=\"/docs/jacoco-resources/greenbar.gif\" width=\"82\" height=\"10\" title=\"37\" alt=\"37\">",
                  "colspan": 1,
                  "rowspan": 1
                },
                {
                  "text": "100%",
                  "colspan": 1,
                  "rowspan": 1
                },
                {
                  "text": "",
                  "colspan": 1,
                  "rowspan": 1
                },
                {
                  "text": "n/a",
                  "colspan": 1,
                  "rowspan": 1
                },
                {
                  "text": "0",
                  "colspan": 1,
                  "rowspan": 1
                },
                {
                  "text": "1",
                  "colspan": 1,
                  "rowspan": 1
                },
                {
                  "text": "0",
                  "colspan": 1,
                  "rowspan": 1
                },
                {
                  "text": "9",
                  "colspan": 1,
                  "rowspan": 1
                },
                {
                  "text": "0",
                  "colspan": 1,
                  "rowspan": 1
                },
                {
                  "text": "1",
                  "colspan": 1,
                  "rowspan": 1
                }
              ],
              [
                {
                  "text": "<a href=\"S3MultipartHandler.java.json#L171\" class=\"el_method\">listParts(ServerRequest)</a>",
                  "colspan": 1,
                  "rowspan": 1
                },
                {
                  "text": "<img src=\"/docs/jacoco-resources/greenbar.gif\" width=\"80\" height=\"10\" title=\"36\" alt=\"36\">",
                  "colspan": 1,
                  "rowspan": 1
                },
                {
                  "text": "100%",
                  "colspan": 1,
                  "rowspan": 1
                },
                {
                  "text": "",
                  "colspan": 1,
                  "rowspan": 1
                },
                {
                  "text": "n/a",
                  "colspan": 1,
                  "rowspan": 1
                },
                {
                  "text": "0",
                  "colspan": 1,
                  "rowspan": 1
                },
                {
                  "text": "1",
                  "colspan": 1,
                  "rowspan": 1
                },
                {
                  "text": "0",
                  "colspan": 1,
                  "rowspan": 1
                },
                {
                  "text": "9",
                  "colspan": 1,
                  "rowspan": 1
                },
                {
                  "text": "0",
                  "colspan": 1,
                  "rowspan": 1
                },
                {
                  "text": "1",
                  "colspan": 1,
                  "rowspan": 1
                }
              ],
              [
                {
                  "text": "<a href=\"S3MultipartHandler.java.json#L44\" class=\"el_method\">initiateMultipartUpload(ServerRequest)</a>",
                  "colspan": 1,
                  "rowspan": 1
                },
                {
                  "text": "<img src=\"/docs/jacoco-resources/greenbar.gif\" width=\"77\" height=\"10\" title=\"35\" alt=\"35\">",
                  "colspan": 1,
                  "rowspan": 1
                },
                {
                  "text": "100%",
                  "colspan": 1,
                  "rowspan": 1
                },
                {
                  "text": "",
                  "colspan": 1,
                  "rowspan": 1
                },
                {
                  "text": "n/a",
                  "colspan": 1,
                  "rowspan": 1
                },
                {
                  "text": "0",
                  "colspan": 1,
                  "rowspan": 1
                },
                {
                  "text": "1",
                  "colspan": 1,
                  "rowspan": 1
                },
                {
                  "text": "0",
                  "colspan": 1,
                  "rowspan": 1
                },
                {
                  "text": "10",
                  "colspan": 1,
                  "rowspan": 1
                },
                {
                  "text": "0",
                  "colspan": 1,
                  "rowspan": 1
                },
                {
                  "text": "1",
                  "colspan": 1,
                  "rowspan": 1
                }
              ],
              [
                {
                  "text": "<a href=\"S3MultipartHandler.java.json#L141\" class=\"el_method\">abortMultipartUpload(ServerRequest)</a>",
                  "colspan": 1,
                  "rowspan": 1
                },
                {
                  "text": "<img src=\"/docs/jacoco-resources/greenbar.gif\" width=\"60\" height=\"10\" title=\"27\" alt=\"27\">",
                  "colspan": 1,
                  "rowspan": 1
                },
                {
                  "text": "100%",
                  "colspan": 1,
                  "rowspan": 1
                },
                {
                  "text": "",
                  "colspan": 1,
                  "rowspan": 1
                },
                {
                  "text": "n/a",
                  "colspan": 1,
                  "rowspan": 1
                },
                {
                  "text": "0",
                  "colspan": 1,
                  "rowspan": 1
                },
                {
                  "text": "1",
                  "colspan": 1,
                  "rowspan": 1
                },
                {
                  "text": "0",
                  "colspan": 1,
                  "rowspan": 1
                },
                {
                  "text": "7",
                  "colspan": 1,
                  "rowspan": 1
                },
                {
                  "text": "0",
                  "colspan": 1,
                  "rowspan": 1
                },
                {
                  "text": "1",
                  "colspan": 1,
                  "rowspan": 1
                }
              ],
              [
                {
                  "text": "<a href=\"S3MultipartHandler.java.json#L99\" class=\"el_method\">lambda$uploadPart$1(int, long, MultipartUpload)</a>",
                  "colspan": 1,
                  "rowspan": 1
                },
                {
                  "text": "<img src=\"/docs/jacoco-resources/greenbar.gif\" width=\"53\" height=\"10\" title=\"24\" alt=\"24\">",
                  "colspan": 1,
                  "rowspan": 1
                },
                {
                  "text": "100%",
                  "colspan": 1,
                  "rowspan": 1
                },
                {
                  "text": "",
                  "colspan": 1,
                  "rowspan": 1
                },
                {
                  "text": "n/a",
                  "colspan": 1,
                  "rowspan": 1
                },
                {
                  "text": "0",
                  "colspan": 1,
                  "rowspan": 1
                },
                {
                  "text": "1",
                  "colspan": 1,
                  "rowspan": 1
                },
                {
                  "text": "0",
                  "colspan": 1,
                  "rowspan": 1
                },
                {
                  "text": "8",
                  "colspan": 1,
                  "rowspan": 1
                },
                {
                  "text": "0",
                  "colspan": 1,
                  "rowspan": 1
                },
                {
                  "text": "1",
                  "colspan": 1,
                  "rowspan": 1
                }
              ],
              [
                {
                  "text": "<a href=\"S3MultipartHandler.java.json#L157\" class=\"el_method\">listMultipartUploads(ServerRequest)</a>",
                  "colspan": 1,
                  "rowspan": 1
                },
                {
                  "text": "<img src=\"/docs/jacoco-resources/greenbar.gif\" width=\"40\" height=\"10\" title=\"18\" alt=\"18\">",
                  "colspan": 1,
                  "rowspan": 1
                },
                {
                  "text": "100%",
                  "colspan": 1,
                  "rowspan": 1
                },
                {
                  "text": "",
                  "colspan": 1,
                  "rowspan": 1
                },
                {
                  "text": "n/a",
                  "colspan": 1,
                  "rowspan": 1
                },
                {
                  "text": "0",
                  "colspan": 1,
                  "rowspan": 1
                },
                {
                  "text": "1",
                  "colspan": 1,
                  "rowspan": 1
                },
                {
                  "text": "0",
                  "colspan": 1,
                  "rowspan": 1
                },
                {
                  "text": "5",
                  "colspan": 1,
                  "rowspan": 1
                },
                {
                  "text": "0",
                  "colspan": 1,
                  "rowspan": 1
                },
                {
                  "text": "1",
                  "colspan": 1,
                  "rowspan": 1
                }
              ],
              [
                {
                  "text": "<a href=\"S3MultipartHandler.java.json#L178\" class=\"el_method\">lambda$listParts$9(String, String, MultipartUpload)</a>",
                  "colspan": 1,
                  "rowspan": 1
                },
                {
                  "text": "<img src=\"/docs/jacoco-resources/greenbar.gif\" width=\"35\" height=\"10\" title=\"16\" alt=\"16\">",
                  "colspan": 1,
                  "rowspan": 1
                },
                {
                  "text": "100%",
                  "colspan": 1,
                  "rowspan": 1
                },
                {
                  "text": "",
                  "colspan": 1,
                  "rowspan": 1
                },
                {
                  "text": "n/a",
                  "colspan": 1,
                  "rowspan": 1
                },
                {
                  "text": "0",
                  "colspan": 1,
                  "rowspan": 1
                },
                {
                  "text": "1",
                  "colspan": 1,
                  "rowspan": 1
                },
                {
                  "text": "0",
                  "colspan": 1,
                  "rowspan": 1
                },
                {
                  "text": "5",
                  "colspan": 1,
                  "rowspan": 1
                },
                {
                  "text": "0",
                  "colspan": 1,
                  "rowspan": 1
                },
                {
                  "text": "1",
                  "colspan": 1,
                  "rowspan": 1
                }
              ],
              [
                {
                  "text": "<a href=\"S3MultipartHandler.java.json#L123\" class=\"el_method\">lambda$completeMultipartUpload$3(String, String, MultipartUpload)</a>",
                  "colspan": 1,
                  "rowspan": 1
                },
                {
                  "text": "<img src=\"/docs/jacoco-resources/greenbar.gif\" width=\"28\" height=\"10\" title=\"13\" alt=\"13\">",
                  "colspan": 1,
                  "rowspan": 1
                },
                {
                  "text": "100%",
                  "colspan": 1,
                  "rowspan": 1
                },
                {
                  "text": "",
                  "colspan": 1,
                  "rowspan": 1
                },
                {
                  "text": "n/a",
                  "colspan": 1,
                  "rowspan": 1
                },
                {
                  "text": "0",
                  "colspan": 1,
                  "rowspan": 1
                },
                {
                  "text": "1",
                  "colspan": 1,
                  "rowspan": 1
                },
                {
                  "text": "0",
                  "colspan": 1,
                  "rowspan": 1
                },
                {
                  "text": "3",
                  "colspan": 1,
                  "rowspan": 1
                },
                {
                  "text": "0",
                  "colspan": 1,
                  "rowspan": 1
                },
                {
                  "text": "1",
                  "colspan": 1,
                  "rowspan": 1
                }
              ],
              [
                {
                  "text": "<a href=\"S3MultipartHandler.java.json#L127\" class=\"el_method\">lambda$completeMultipartUpload$2(String, String)</a>",
                  "colspan": 1,
                  "rowspan": 1
                },
                {
                  "text": "<img src=\"/docs/jacoco-resources/greenbar.gif\" width=\"28\" height=\"10\" title=\"13\" alt=\"13\">",
                  "colspan": 1,
                  "rowspan": 1
                },
                {
                  "text": "100%",
                  "colspan": 1,
                  "rowspan": 1
                },
                {
                  "text": "",
                  "colspan": 1,
                  "rowspan": 1
                },
                {
                  "text": "n/a",
                  "colspan": 1,
                  "rowspan": 1
                },
                {
                  "text": "0",
                  "colspan": 1,
                  "rowspan": 1
                },
                {
                  "text": "1",
                  "colspan": 1,
                  "rowspan": 1
                },
                {
                  "text": "0",
                  "colspan": 1,
                  "rowspan": 1
                },
                {
                  "text": "5",
                  "colspan": 1,
                  "rowspan": 1
                },
                {
                  "text": "0",
                  "colspan": 1,
                  "rowspan": 1
                },
                {
                  "text": "1",
                  "colspan": 1,
                  "rowspan": 1
                }
              ],
              [
                {
                  "text": "<a href=\"S3MultipartHandler.java.json#L146\" class=\"el_method\">lambda$abortMultipartUpload$4(MultipartUpload)</a>",
                  "colspan": 1,
                  "rowspan": 1
                },
                {
                  "text": "<img src=\"/docs/jacoco-resources/greenbar.gif\" width=\"24\" height=\"10\" title=\"11\" alt=\"11\">",
                  "colspan": 1,
                  "rowspan": 1
                },
                {
                  "text": "100%",
                  "colspan": 1,
                  "rowspan": 1
                },
                {
                  "text": "",
                  "colspan": 1,
                  "rowspan": 1
                },
                {
                  "text": "n/a",
                  "colspan": 1,
                  "rowspan": 1
                },
                {
                  "text": "0",
                  "colspan": 1,
                  "rowspan": 1
                },
                {
                  "text": "1",
                  "colspan": 1,
                  "rowspan": 1
                },
                {
                  "text": "0",
                  "colspan": 1,
                  "rowspan": 1
                },
                {
                  "text": "3",
                  "colspan": 1,
                  "rowspan": 1
                },
                {
                  "text": "0",
                  "colspan": 1,
                  "rowspan": 1
                },
                {
                  "text": "1",
                  "colspan": 1,
                  "rowspan": 1
                }
              ],
              [
                {
                  "text": "<a href=\"S3MultipartHandler.java.json#L160\" class=\"el_method\">lambda$listMultipartUploads$5(MultipartUpload)</a>",
                  "colspan": 1,
                  "rowspan": 1
                },
                {
                  "text": "<img src=\"/docs/jacoco-resources/greenbar.gif\" width=\"22\" height=\"10\" title=\"10\" alt=\"10\">",
                  "colspan": 1,
                  "rowspan": 1
                },
                {
                  "text": "100%",
                  "colspan": 1,
                  "rowspan": 1
                },
                {
                  "text": "",
                  "colspan": 1,
                  "rowspan": 1
                },
                {
                  "text": "n/a",
                  "colspan": 1,
                  "rowspan": 1
                },
                {
                  "text": "0",
                  "colspan": 1,
                  "rowspan": 1
                },
                {
                  "text": "1",
                  "colspan": 1,
                  "rowspan": 1
                },
                {
                  "text": "0",
                  "colspan": 1,
                  "rowspan": 1
                },
                {
                  "text": "2",
                  "colspan": 1,
                  "rowspan": 1
                },
                {
                  "text": "0",
                  "colspan": 1,
                  "rowspan": 1
                },
                {
                  "text": "1",
                  "colspan": 1,
                  "rowspan": 1
                }
              ],
              [
                {
                  "text": "<a href=\"S3MultipartHandler.java.json#L179\" class=\"el_method\">lambda$listParts$7(UploadPart)</a>",
                  "colspan": 1,
                  "rowspan": 1
                },
                {
                  "text": "<img src=\"/docs/jacoco-resources/greenbar.gif\" width=\"15\" height=\"10\" title=\"7\" alt=\"7\">",
                  "colspan": 1,
                  "rowspan": 1
                },
                {
                  "text": "100%",
                  "colspan": 1,
                  "rowspan": 1
                },
                {
                  "text": "",
                  "colspan": 1,
                  "rowspan": 1
                },
                {
                  "text": "n/a",
                  "colspan": 1,
                  "rowspan": 1
                },
                {
                  "text": "0",
                  "colspan": 1,
                  "rowspan": 1
                },
                {
                  "text": "1",
                  "colspan": 1,
                  "rowspan": 1
                },
                {
                  "text": "0",
                  "colspan": 1,
                  "rowspan": 1
                },
                {
                  "text": "1",
                  "colspan": 1,
                  "rowspan": 1
                },
                {
                  "text": "0",
                  "colspan": 1,
                  "rowspan": 1
                },
                {
                  "text": "1",
                  "colspan": 1,
                  "rowspan": 1
                }
              ],
              [
                {
                  "text": "<a href=\"S3MultipartHandler.java.json#L38\" class=\"el_method\">S3MultipartHandler(ReactiveMultipartUploadService)</a>",
                  "colspan": 1,
                  "rowspan": 1
                },
                {
                  "text": "<img src=\"/docs/jacoco-resources/greenbar.gif\" width=\"13\" height=\"10\" title=\"6\" alt=\"6\">",
                  "colspan": 1,
                  "rowspan": 1
                },
                {
                  "text": "100%",
                  "colspan": 1,
                  "rowspan": 1
                },
                {
                  "text": "",
                  "colspan": 1,
                  "rowspan": 1
                },
                {
                  "text": "n/a",
                  "colspan": 1,
                  "rowspan": 1
                },
                {
                  "text": "0",
                  "colspan": 1,
                  "rowspan": 1
                },
                {
                  "text": "1",
                  "colspan": 1,
                  "rowspan": 1
                },
                {
                  "text": "0",
                  "colspan": 1,
                  "rowspan": 1
                },
                {
                  "text": "3",
                  "colspan": 1,
                  "rowspan": 1
                },
                {
                  "text": "0",
                  "colspan": 1,
                  "rowspan": 1
                },
                {
                  "text": "1",
                  "colspan": 1,
                  "rowspan": 1
                }
              ],
              [
                {
                  "text": "<a href=\"S3MultipartHandler.java.json#L183\" class=\"el_method\">lambda$listParts$8(ListPartsQuery)</a>",
                  "colspan": 1,
                  "rowspan": 1
                },
                {
                  "text": "<img src=\"/docs/jacoco-resources/greenbar.gif\" width=\"13\" height=\"10\" title=\"6\" alt=\"6\">",
                  "colspan": 1,
                  "rowspan": 1
                },
                {
                  "text": "100%",
                  "colspan": 1,
                  "rowspan": 1
                },
                {
                  "text": "",
                  "colspan": 1,
                  "rowspan": 1
                },
                {
                  "text": "n/a",
                  "colspan": 1,
                  "rowspan": 1
                },
                {
                  "text": "0",
                  "colspan": 1,
                  "rowspan": 1
                },
                {
                  "text": "1",
                  "colspan": 1,
                  "rowspan": 1
                },
                {
                  "text": "0",
                  "colspan": 1,
                  "rowspan": 1
                },
                {
                  "text": "3",
                  "colspan": 1,
                  "rowspan": 1
                },
                {
                  "text": "0",
                  "colspan": 1,
                  "rowspan": 1
                },
                {
                  "text": "1",
                  "colspan": 1,
                  "rowspan": 1
                }
              ],
              [
                {
                  "text": "<a href=\"S3MultipartHandler.java.json#L164\" class=\"el_method\">lambda$listMultipartUploads$6(ListMultipartUploadsQuery)</a>",
                  "colspan": 1,
                  "rowspan": 1
                },
                {
                  "text": "<img src=\"/docs/jacoco-resources/greenbar.gif\" width=\"13\" height=\"10\" title=\"6\" alt=\"6\">",
                  "colspan": 1,
                  "rowspan": 1
                },
                {
                  "text": "100%",
                  "colspan": 1,
                  "rowspan": 1
                },
                {
                  "text": "",
                  "colspan": 1,
                  "rowspan": 1
                },
                {
                  "text": "n/a",
                  "colspan": 1,
                  "rowspan": 1
                },
                {
                  "text": "0",
                  "colspan": 1,
                  "rowspan": 1
                },
                {
                  "text": "1",
                  "colspan": 1,
                  "rowspan": 1
                },
                {
                  "text": "0",
                  "colspan": 1,
                  "rowspan": 1
                },
                {
                  "text": "3",
                  "colspan": 1,
                  "rowspan": 1
                },
                {
                  "text": "0",
                  "colspan": 1,
                  "rowspan": 1
                },
                {
                  "text": "1",
                  "colspan": 1,
                  "rowspan": 1
                }
              ]
            ]
          },
          {
            "type": "paragraph",
            "html": "<div class=\"footer\"><span class=\"right\">Created with <a href=\"http://www.jacoco.org/jacoco\">JaCoCo</a> 0.8.12.202403310830</span></div>"
          }
        ]
      }
    ],
    "lang": "it"
  }
}