{
  "title": "FileSystemVirtualDeviceMapper.java",
  "lang": "it",
  "document": {
    "type": "document",
    "title": "FileSystemVirtualDeviceMapper.java",
    "sections": [
      {
        "type": "section",
        "id": "_filesystemvirtualdevicemapper_java",
        "title": "FileSystemVirtualDeviceMapper.java",
        "level": 1,
        "blocks": [
          {
            "type": "code",
            "html": "<pre>package com.example.magrathea.storageengine.infrastructure.filesystem;\n\nimport com.example.magrathea.storageengine.domain.valueobject.VirtualDevice;\n\nimport java.io.IOException;\nimport java.io.UncheckedIOException;\nimport java.nio.file.Files;\nimport java.nio.file.Path;\n\n/**\n * Maps VirtualDevice instances to filesystem paths.\n * <p>\n * BucketDevice -> devices/bucket/{bucketId}\n * DedupDevice -> devices/dedup/{configurationHash}\n */\npublic class FileSystemVirtualDeviceMapper {\n\n    private final Path devicesRoot;\n\n<span class=\"nc\" id=\"L20\">    public FileSystemVirtualDeviceMapper(Path devicesRoot) {</span>\n<span class=\"nc\" id=\"L21\">        this.devicesRoot = java.util.Objects.requireNonNull(devicesRoot, \"devicesRoot must not be null\");</span>\n        try {\n<span class=\"nc\" id=\"L23\">            Files.createDirectories(devicesRoot);</span>\n<span class=\"nc\" id=\"L24\">        } catch (IOException e) {</span>\n<span class=\"nc\" id=\"L25\">            throw new UncheckedIOException(\"Failed to create devices directory: \" + devicesRoot, e);</span>\n<span class=\"nc\" id=\"L26\">        }</span>\n<span class=\"nc\" id=\"L27\">    }</span>\n\n    /**\n     * Resolves the filesystem path for a given VirtualDevice.\n     */\n    public Path resolveDevicePath(VirtualDevice device) {\n<span class=\"nc bnc\" id=\"L33\" title=\"All 2 branches missed.\">        if (device instanceof VirtualDevice.BucketDevice bd) {</span>\n<span class=\"nc\" id=\"L34\">            return devicesRoot.resolve(\"bucket\")</span>\n<span class=\"nc\" id=\"L35\">                    .resolve(bd.bucketRef().bucketId().value());</span>\n<span class=\"nc bnc\" id=\"L36\" title=\"All 2 branches missed.\">        } else if (device instanceof VirtualDevice.DedupDevice dd) {</span>\n<span class=\"nc\" id=\"L37\">            return devicesRoot.resolve(\"dedup\")</span>\n<span class=\"nc\" id=\"L38\">                    .resolve(dd.configurationHash().value());</span>\n        } else {\n<span class=\"nc\" id=\"L40\">            throw new IllegalArgumentException(\"Unknown VirtualDevice type: \" + device.getClass());</span>\n        }\n    }\n}\n</pre>"
          },
          {
            "type": "paragraph",
            "html": "<div class=\"footer\"><span class=\"right\">Created with <a href=\"http://www.jacoco.org/jacoco\">JaCoCo</a> 0.8.12.202403310830</span></div>"
          }
        ]
      }
    ],
    "lang": "it"
  }
}